argparse_charged/__init__.py
argparse_charged/action.py
argparse_charged/formatter.py
argparse_charged/parser.py
argparse_charged/type_.py
argparse_charged/utils.py
argparse_charged-0.0.1.dist-info/WHEEL
argparse_charged-0.0.1.dist-info/METADATA
argparse_charged-0.0.1.dist-info/RECORD
