Metadata-Version: 2.1
Name: argparse-charged
Version: 0.0.1
Summary: Super-charged argparse for python
License: MIT
Author: pwwang
Author-email: pwwang@pwwang.com
Requires-Python: >=3.7,<4.0
Classifier: License :: OSI Approved :: MIT License
Classifier: Programming Language :: Python :: 3
Classifier: Programming Language :: Python :: 3.7
Classifier: Programming Language :: Python :: 3.8
Classifier: Programming Language :: Python :: 3.9
Classifier: Programming Language :: Python :: 3.10
Classifier: Programming Language :: Python :: 3.11
Requires-Dist: python-simpleconf (>=0.5.7,<0.6.0)
